LICENSE.txt
MANIFEST.in
README.md
setup.py
apps/hs_resize.py
apps/kraken.py
apps/kraken_run
apps/pond.py
apps/pond_run
apps/portal.py
apps/portal_run
apps/valve.py
apps/valve_run
apps/valveconfig.py
apps/valveconfig_run
aquaduct/__init__.py
aquaduct.egg-info/PKG-INFO
aquaduct.egg-info/SOURCES.txt
aquaduct.egg-info/dependency_links.txt
aquaduct.egg-info/requires.txt
aquaduct.egg-info/top_level.txt
aquaduct/apps/__init__.py
aquaduct/apps/chord.py
aquaduct/apps/data.py
aquaduct/apps/valve/__init__.py
aquaduct/apps/valve/clusters.py
aquaduct/apps/valve/core.py
aquaduct/apps/valve/data.py
aquaduct/apps/valve/helpers.py
aquaduct/apps/valve/spath.py
aquaduct/apps/valve/worker.py
aquaduct/apps/valveconfig/__init__.py
aquaduct/apps/valveconfig/defaults.py
aquaduct/apps/valveconfig/icon.gif
aquaduct/apps/valveconfig/info.gif
aquaduct/apps/valveconfig/logo.gif
aquaduct/apps/valveconfig/utils.py
aquaduct/apps/valveconfig/warning.gif
aquaduct/geom/__init__.py
aquaduct/geom/cluster.py
aquaduct/geom/cluster_available_methods.py
aquaduct/geom/convexhull.py
aquaduct/geom/hdr.py
aquaduct/geom/hdr_contour.py
aquaduct/geom/master.py
aquaduct/geom/pca.py
aquaduct/geom/pocket.py
aquaduct/geom/smooth.py
aquaduct/geom/smooth_available_methods.py
aquaduct/geom/traces.py
aquaduct/traj/__init__.py
aquaduct/traj/barber.py
aquaduct/traj/dumps.py
aquaduct/traj/inlets.py
aquaduct/traj/paths.py
aquaduct/traj/sandwich.py
aquaduct/utils/__init__.py
aquaduct/utils/clui.py
aquaduct/utils/filecache.py
aquaduct/utils/helpers.py
aquaduct/utils/maths.py
aquaduct/utils/multip.py
aquaduct/utils/sets.py
aquaduct/utils/sr.py
aquaduct/visual/__init__.py
aquaduct/visual/cmaps.py
aquaduct/visual/helpers.py
aquaduct/visual/pymol_cgo.py
aquaduct/visual/pymol_connector.py
aquaduct/visual/quickplot.py