Metadata-Version: 2.1
Name: aquaduct
Version: 1.0.11
Summary: Tracing molecules in MD simulation
Home-page: http://aquaduct.pl
Author: Tomasz Magdziarz, Michał Banas, Alicja Płuciennik, Michał Stolarczyk
Author-email: info@aquaduct.pl
License: GNU GPL v3
Project-URL: Source, https://github.com/TUNNELING-GROUP/aqua-duct
Project-URL: Documentation, https://tunneling-group.github.io/aqua-duct/
Project-URL: Tracker, https://github.com/TUNNELING-GROUP/aqua-duct/issues/
Keywords: molecular-dynamics solvent
Platform: UNKNOWN
Classifier: Development Status :: 5 - Production/Stable
Classifier: Environment :: Console
Classifier: Intended Audience :: Science/Research
Classifier: Operating System :: POSIX
Classifier: Programming Language :: Python
Provides: aquaduct
Requires-Python: >=3
Provides-Extra: full_pymol
Provides-Extra: graphs
